fpga_i2c_bridge/__init__.py
fpga_i2c_bridge/__main__.py
fpga_i2c_bridge/appliance.py
fpga_i2c_bridge/i2c.py
fpga_i2c_bridge/i2c_dummy.py
fpga_i2c_bridge/sensor.py
fpga_i2c_bridge/net/__init__.py
fpga_i2c_bridge/net/error.py
fpga_i2c_bridge/net/packet.py
fpga_i2c_bridge/test/__init__.py
fpga_i2c_bridge/test/test_appliance.py
fpga_i2c_bridge/test/test_i2c.py
fpga_i2c_bridge/util/Logger.py
fpga_i2c_bridge/util/__init__.py
fpga_i2c_bridge/util/crc.py
fpga_i2c_bridge-0.2.4.dist-info/LICENSE
fpga_i2c_bridge-0.2.4.dist-info/METADATA
fpga_i2c_bridge-0.2.4.dist-info/WHEEL
fpga_i2c_bridge-0.2.4.dist-info/top_level.txt
fpga_i2c_bridge-0.2.4.dist-info/RECORD
